{
  "shared_settings": {
    "aggregation_strategy_keyword": "bulyan",
    "remove_clients": "true",
    "dataset_keyword": "femnist_iid",
    "num_of_rounds": 10,
    "num_of_clients": 20,
    "num_of_malicious_clients": 2,
    "attack_type": "label_flipping",
    "show_plots": "false",
    "save_plots": "true",
    "save_csv": "true",
    "training_device": "cpu",
    "cpus_per_client": 1,
    "gpus_per_client": 0.0,
    "trust_threshold": 0.15,
    "reputation_threshold": 0.15,
    "beta_value": 0.75,
    "num_of_clusters": 1,
    "Kp": 1,
    "Ki": 0.05,
    "Kd": 0.05,
    "num_krum_selections": 16,
    "training_subset_fraction": 0.9,
    "min_fit_clients": 20,
    "min_evaluate_clients": 20,
    "min_available_clients": 20,
    "evaluate_metrics_aggregation_fn": "weighted_average",
    "num_of_client_epochs": 3,
    "batch_size": 10,
    "preserve_dataset": "true",
    "begin_removing_from_round": 2
  },
  "simulation_strategies": [
    {}
  ]
}